README.rst
setup.cfg
setup.py
magus/__init__.py
magus/inspect.py
magus/version.py
magus.egg-info/PKG-INFO
magus.egg-info/SOURCES.txt
magus.egg-info/dependency_links.txt
magus.egg-info/not-zip-safe
magus.egg-info/top_level.txt