Metadata-Version: 1.2
Name: magus
Version: 0.0.1
Summary: Utilities for code inspection and transformation
Home-page: UNKNOWN
Author: Alex Carney
Author-email: alcarneyme@gmail.com
License: MIT
Platform: UNKNOWN
Classifier: Development Status :: 3 - Alpha
Classifier: License :: OSI Approved :: MIT License
Classifier: Programming Language :: Python :: 3.5
Classifier: Programming Language :: Python :: 3.6
Classifier: Programming Language :: Python :: 3 :: Only
Requires-Python: >=3.0
